{"delimiter":",","columns":[{"label":"Account Number"},{"label":"Trade Date"},{"field":"date","format":"yyyy-MM-dd","label":"Settlement Date"},{"label":"Transaction Type"},{"field":"note","label":"Transaction Description"},{"field":"type","format":"DEPOSIT=Deposit;REMOVAL=Withdrawal|Removal;INTEREST=Interest;INTEREST_CHARGE=Interest Charge;DIVIDENDS=Dividend;FEES=Fees;FEES_REFUND=Fees Refund;TAXES=Taxes;TAX_REFUND=Tax Refund;BUY=Buy;SELL=Sell;TRANSFER_IN=Transfer (Inbound);TRANSFER_OUT=Transfer (Outbound)","label":"Type"},{"label":"Investment Name"},{"field":"ticker","label":"Symbol"},{"field":"shares","format":"0,000.00","label":"Shares"},{"field":"value","format":"0,000.00","label":"Share Price"},{"field":"value","format":"0,000.00","label":"Principal Amount"},{"label":"Commissions and Fees"},{"label":"Net Amount"},{"label":"Accrued Interest"},{"label":"Account Type"},{"label":""}],"isFirstLineHeader":true,"skipLines":0,"label":"Vanguard_Roth_IRA_CSV_works.json","encoding":"UTF-8","target":"account-transaction"}